blusky/__init__.py
blusky/datasets/__init__.py
blusky/transforms/__init__.py
blusky/transforms/apply_father_wavelet_1d.py
blusky/transforms/apply_father_wavelet_2d.py
blusky/transforms/cascade_1d.py
blusky/transforms/cascade_2d.py
blusky/transforms/cascade_tree.py
blusky/transforms/default_decimation.py
blusky/transforms/i_decimation_method.py
blusky/transforms/transform_factories_2d.py
blusky/transforms/tests/__init__.py
blusky/transforms/tests/test_apply_father_wavelet_2d.py
blusky/transforms/tests/test_cascade_1d.py
blusky/transforms/tests/test_cascade_2d.py
blusky/transforms/tests/test_decimation.py
blusky/utils/__init__.py
blusky/utils/pad_1d.py
blusky/utils/pad_2d.py
blusky/utils/tiled_iterator.py
blusky/utils/visualize_2d.py
blusky/utils/tests/__init__.py
blusky/utils/tests/test_pad_2d.py
blusky/utils/tests/test_tiled_iterator.py
blusky/wavelets/__init__.py
blusky/wavelets/gabor2d.py
blusky/wavelets/gabor_1d.py
blusky/wavelets/i_wavelet_1d.py
blusky/wavelets/i_wavelet_2d.py
blusky/wavelets/morlet2d.py
blusky/wavelets/morlet_1d.py
blusky/wavelets/wavelet_factories_1d.py
blusky/wavelets/wavelet_factories_2d.py
blusky/wavelets/tests/__init__.py
blusky/wavelets/tests/test_gabor2d.py
blusky/wavelets/tests/test_morlet2d.py
blusky-0.0.2.dist-info/LICENSE.txt
blusky-0.0.2.dist-info/METADATA
blusky-0.0.2.dist-info/WHEEL
blusky-0.0.2.dist-info/entry_points.txt
blusky-0.0.2.dist-info/top_level.txt
blusky-0.0.2.dist-info/RECORD
